obs/__init__.py
obs/auth.py
obs/bucket.py
obs/bulktasks.py
obs/cache.py
obs/client.py
obs/const.py
obs/convertor.py
obs/extension.py
obs/http2.py
obs/ilog.py
obs/loadtoken.py
obs/locks.py
obs/model.py
obs/progress.py
obs/searchmethod.py
obs/transfer.py
obs/util.py
huawei_obs-0.0.1.dist-info/METADATA
huawei_obs-0.0.1.dist-info/WHEEL
huawei_obs-0.0.1.dist-info/top_level.txt
huawei_obs-0.0.1.dist-info/RECORD
