Metadata-Version: 2.1
Name: huawei-obs
Version: 0.0.1
Summary: huawei yun obs client
Home-page: UNKNOWN
Author: sheng_xc
Author-email: sheng_xc@126.com
License: UNKNOWN
Platform: UNKNOWN
Classifier: Programming Language :: Python :: 3
Classifier: License :: OSI Approved :: MIT License
Classifier: Operating System :: OS Independent
Requires-Python: >=3.5
